multiminio/__init__.py
multiminio/multiminio.py
multiminio-1.0.2.dist-info/entry_points.txt
multiminio-1.0.2.dist-info/LICENSE
multiminio-1.0.2.dist-info/METADATA
multiminio-1.0.2.dist-info/WHEEL
multiminio-1.0.2.dist-info/RECORD
