Metadata-Version: 2.1
Name: multiminio
Version: 1.0.2
Summary: MultiMinio: provides failover and health-checking for applications using multiple Minio object storage instances, ensuring uninterrupted access and resilience.
Home-page: https://github.com/asuiu/multiminio
License: MIT
Author: Andrei Suiu
Author-email: andrei.suiu@gmail.com
Requires-Python: >=3.8,<4.0.0
Classifier: License :: OSI Approved :: MIT License
Classifier: Programming Language :: Python :: 3
Classifier: Programming Language :: Python :: 3.8
Classifier: Programming Language :: Python :: 3.9
Classifier: Programming Language :: Python :: 3.10
Classifier: Programming Language :: Python :: 3.11
Requires-Dist: StrEnum (>=0.4.0)
Requires-Dist: minio (>=7.0.0)
Requires-Dist: requests (>=2.25.1)
Requires-Dist: streamerate (>=1)
Requires-Dist: tsx (>=0.1.4)
Project-URL: Repository, https://github.com/asuiu/multiminio
